eb2-0.0.2.data/scripts/eb2
eb2-0.0.2.dist-info/DESCRIPTION.rst
eb2-0.0.2.dist-info/METADATA
eb2-0.0.2.dist-info/RECORD
eb2-0.0.2.dist-info/WHEEL
eb2-0.0.2.dist-info/metadata.json
eb2-0.0.2.dist-info/top_level.txt
lib/__init__.py
lib/ec2.py
lib/utils.py
objects/__init__.py
objects/exceptions.py
