Metadata-Version: 2.0
Name: eb2
Version: 0.0.2
Summary: Elastic Beanstalk ssh cli using the internal IP address
Home-page: https://github.com/jonathortense/homebrew-eb2
Author: Jonathas Hortense
Author-email: jonathas.hortense@daliaresearch.com
License: UNKNOWN
Platform: UNKNOWN
Requires-Dist: awsebcli
Requires-Dist: boto3
